webreview/VERSION
webreview/__init__.py
webreview/test_auth.py
webreview/webreview.py
webreview/webreview_test.py
webreview-0.3.1.dist-info/LICENSE
webreview-0.3.1.dist-info/METADATA
webreview-0.3.1.dist-info/WHEEL
webreview-0.3.1.dist-info/top_level.txt
webreview-0.3.1.dist-info/RECORD
