Metadata-Version: 2.1
Name: webreview
Version: 0.3.1
Summary: Client library for the WebReview static site staging service.
Home-page: https://github.com/grow/webreview-client
Author: Grow SDK Authors
Author-email: code@grow.io
License: MIT
Keywords: grow,cms,static site generator,s3,google cloud storage,content management
Platform: UNKNOWN
Classifier: Environment :: Web Environment
Classifier: Intended Audience :: Developers
Classifier: License :: OSI Approved :: MIT License
Classifier: Natural Language :: English
Classifier: Operating System :: OS Independent
Classifier: Programming Language :: Python :: 3
Classifier: Programming Language :: Python
Classifier: Topic :: Internet :: WWW/HTTP :: Dynamic Content
Classifier: Topic :: Software Development :: Libraries :: Python Modules
Requires-Dist: google-api-python-client (>=1.3.2)
Requires-Dist: httplib2 (>=0.17.0)
Requires-Dist: oauth2client (>=3.0.0)
Requires-Dist: progressbar2 (>=3.34.3)
Requires-Dist: protorpc (>=0.12.0)
Requires-Dist: requests (>=2.18.4)
